bootstrapmex
