Metadata-Version: 1.1
Name: bootstrapmex
Version: 0.5
Summary: Calculate statistical features from text
Home-page: UNKNOWN
Author: Ganes
Author-email: shivam5992@gmail.com
License: MIT
Platform: UNKNOWN
Classifier: Programming Language :: Python
Classifier: Programming Language :: Python :: 3.5
Classifier: Programming Language :: Python :: 3.6
Classifier: Programming Language :: Python :: 3.7
